news_tracking/__init__.py
news_tracking/news_tracking_evaluation.py
news_tracking/news_tracking_kmeans.py
news_tracking/news_tracking_miranda.py
news_tracking/news_tracking_miranda_training.py
news_tracking-1.0.2.202209211710.dist-info/AUTHORS
news_tracking-1.0.2.202209211710.dist-info/LICENSE
news_tracking-1.0.2.202209211710.dist-info/METADATA
news_tracking-1.0.2.202209211710.dist-info/WHEEL
news_tracking-1.0.2.202209211710.dist-info/entry_points.txt
news_tracking-1.0.2.202209211710.dist-info/top_level.txt
news_tracking-1.0.2.202209211710.dist-info/RECORD
