Metadata-Version: 2.1
Name: news-tracking
Version: 1.0.2.202209211710
Summary: Programs used to manage experiments with the document_tracking infrastructure.
Home-page: https://gitlab.univ-lr.fr/cross-lingual-event-tracking/developpement/from-documents-to-events/news_clustering_in_multiple_languages
Author: Guillaume Bernard
Author-email: contact@guillaume-bernard.fr
License: GPLv3 License and 3-Clause BSD Licence
Project-URL: Bug Tracker, https://gitlab.univ-lr.fr/cross-lingual-event-tracking/developpement/from-documents-to-events/news_clustering_in_multiple_languages/-/issues
Platform: UNKNOWN
Classifier: Programming Language :: Python :: 3.9
Classifier: License :: OSI Approved :: GNU General Public License v3 (GPLv3)
Classifier: Topic :: Scientific/Engineering :: Artificial Intelligence
Classifier: Intended Audience :: Science/Research
Classifier: Topic :: Scientific/Engineering :: Information Analysis
Classifier: Operating System :: POSIX :: Linux
Classifier: Intended Audience :: Science/Research
License-File: LICENSE
License-File: AUTHORS
Requires-Dist: document-tracking (>=1.0.2.202208310824)
Requires-Dist: document-tracking-resources (>=1.0.1.202208310822)
Requires-Dist: matplotlib (>=3.6.0)
Requires-Dist: numpy (>=1.22.0)
Requires-Dist: pandas (>=1.5.0)
Requires-Dist: scikit-learn (>=1.1.2)
Requires-Dist: setuptools (>=59.6.0)
Requires-Dist: tqdm (>=4.64.1)
